[
  {
    "timestamp": "2025-11-08T08:17:34.061661",
    "type": "dawn_dispatch",
    "report": "ğŸŒ… DAWN DISPATCH â€” 2025-11-08T08:17:34.054585\nâ•â•â•â•â•â•â•â•â•â•â•â•â•â•â•â•â•â•â•â•â•â•â•â•â•â•â•â•â•â•â•â•â•â•â•â•â•â•â•â•â•â•â•â•â•â•â•â•â•â•â•\n\nğŸ’° TREASURY STATUS\nâ€¢ Store Revenue: $0.00\nâ€¢ Orders Processed: 0\nâ€¢ Average Order Value: $0.00\nâ€¢ Store Status: OFFLINE\n\nğŸ“± SOCIAL DOMINION\nâ€¢ Twitter Proclamations: 0\nâ€¢ Buffer Posts: 0\nâ€¢ Total Interactions: 0\nâ€¢ Platform Status: Twitter: OFFLINE, Buffer: 0 platforms\n\nâš¡ SYSTEM SOVEREIGNTY\nâ€¢ Health Score: 25.0%\nâ€¢ Uptime Status: Systems CRITICAL\nâ€¢ Services Online: 1/4\n\nğŸ“œ CODEX LEDGER\nâ€¢ Daily Proclamations: 11\nâ€¢ Ledger Status: ACTIVE\nâ€¢ Last Update: 2025-11-08T03:17:34\n\nğŸ”¥ DIGITAL SOVEREIGNTY STATUS: ğŸ”´ CRITICAL\n\nâ•â•â•â•â•â•â•â•â•â•â•â•â•â•â•â•â•â•â•â•â•â•â•â•â•â•â•â•â•â•â•â•â•â•â•â•â•â•â•â•â•â•â•â•â•â•â•â•â•â•â•\nGenerated by Codex Dawn Dispatch System v2.0\nPowered by The Merritt Methodâ„¢",
    "metrics": {
      "store": {
        "revenue": "$0.00",
        "orders": 0,
        "status": "OFFLINE",
        "avg_order_value": "$0.00"
      },
      "social": {
        "twitter_posts": 0,
        "buffer_posts": 0,
        "total_interactions": 0,
        "platform_status": ["Twitter: OFFLINE", "Buffer: 0 platforms"],
        "connected_platforms": 0
      },
      "system": {
        "uptime": "Systems CRITICAL",
        "services": {
          "Dashboard": true,
          "WooCommerce": false,
          "Twitter": false,
          "Buffer": false
        },
        "health_score": 25.0
      },
      "ledger": {
        "proclamations": 11,
        "status": "ACTIVE",
        "last_update": "2025-11-08T03:17:34.062039"
      }
    }
  },
  {
    "timestamp": "2025-11-08T08:17:34.066888",
    "type": "dawn_dispatch",
    "report": "ğŸŒ… TEST DAWN DISPATCH\nThis is a test report for archive functionality.\nGenerated at: 2024-01-01T00:00:00Z",
    "metrics": {
      "store": {
        "revenue": "$0.00",
        "orders": 0,
        "status": "OFFLINE",
        "avg_order_value": "$0.00"
      },
      "social": {
        "twitter_posts": 0,
        "buffer_posts": 0,
        "total_interactions": 0,
        "platform_status": ["Twitter: OFFLINE", "Buffer: 0 platforms"],
        "connected_platforms": 0
      },
      "system": {
        "uptime": "Systems CRITICAL",
        "services": {
          "Dashboard": true,
          "WooCommerce": false,
          "Twitter": false,
          "Buffer": false
        },
        "health_score": 25.0
      },
      "ledger": {
        "proclamations": 11,
        "status": "ACTIVE",
        "last_update": "2025-11-08T03:17:34.067170"
      }
    }
  },
  {
    "timestamp": "2025-11-08T08:18:08.855024",
    "type": "dawn_dispatch",
    "report": "ğŸŒ… DAWN DISPATCH â€” 2025-11-08T08:18:08.854618\nâ•â•â•â•â•â•â•â•â•â•â•â•â•â•â•â•â•â•â•â•â•â•â•â•â•â•â•â•â•â•â•â•â•â•â•â•â•â•â•â•â•â•â•â•â•â•â•â•â•â•â•\n\nğŸ’° TREASURY STATUS\nâ€¢ Store Revenue: $0.00\nâ€¢ Orders Processed: 0\nâ€¢ Average Order Value: $0.00\nâ€¢ Store Status: OFFLINE\n\nğŸ“± SOCIAL DOMINION\nâ€¢ Twitter Proclamations: 0\nâ€¢ Buffer Posts: 0\nâ€¢ Total Interactions: 0\nâ€¢ Platform Status: Twitter: OFFLINE, Buffer: 0 platforms\n\nâš¡ SYSTEM SOVEREIGNTY\nâ€¢ Health Score: 25.0%\nâ€¢ Uptime Status: Systems CRITICAL\nâ€¢ Services Online: 1/4\n\nğŸ“œ CODEX LEDGER\nâ€¢ Daily Proclamations: 11\nâ€¢ Ledger Status: ACTIVE\nâ€¢ Last Update: 2025-11-08T03:18:08\n\nğŸ”¥ DIGITAL SOVEREIGNTY STATUS: ğŸ”´ CRITICAL\n\nâ•â•â•â•â•â•â•â•â•â•â•â•â•â•â•â•â•â•â•â•â•â•â•â•â•â•â•â•â•â•â•â•â•â•â•â•â•â•â•â•â•â•â•â•â•â•â•â•â•â•â•\nGenerated by Codex Dawn Dispatch System v2.0\nPowered by The Merritt Methodâ„¢",
    "metrics": {
      "store": {
        "revenue": "$0.00",
        "orders": 0,
        "status": "OFFLINE",
        "avg_order_value": "$0.00"
      },
      "social": {
        "twitter_posts": 0,
        "buffer_posts": 0,
        "total_interactions": 0,
        "platform_status": ["Twitter: OFFLINE", "Buffer: 0 platforms"],
        "connected_platforms": 0
      },
      "system": {
        "uptime": "Systems CRITICAL",
        "services": {
          "Dashboard": true,
          "WooCommerce": false,
          "Twitter": false,
          "Buffer": false
        },
        "health_score": 25.0
      },
      "ledger": {
        "proclamations": 11,
        "status": "ACTIVE",
        "last_update": "2025-11-08T03:18:08.855496"
      }
    }
  },
  {
    "timestamp": "2025-11-08T09:17:43.458085",
    "type": "dawn_dispatch",
    "report": "ğŸŒ… DAWN DISPATCH â€” 2025-11-08T09:17:43.455467\nâ•â•â•â•â•â•â•â•â•â•â•â•â•â•â•â•â•â•â•â•â•â•â•â•â•â•â•â•â•â•â•â•â•â•â•â•â•â•â•â•â•â•â•â•â•â•â•â•â•â•â•\n\nğŸ’° TREASURY STATUS\nâ€¢ Store Revenue: $0.00\nâ€¢ Orders Processed: 0\nâ€¢ Average Order Value: $0.00\nâ€¢ Store Status: OFFLINE\n\nğŸ“± SOCIAL DOMINION\nâ€¢ Twitter Proclamations: 0\nâ€¢ Buffer Posts: 0\nâ€¢ Total Interactions: 0\nâ€¢ Platform Status: Twitter: OFFLINE, Buffer: 0 platforms\n\nâš¡ SYSTEM SOVEREIGNTY\nâ€¢ Health Score: 25.0%\nâ€¢ Uptime Status: Systems CRITICAL\nâ€¢ Services Online: 1/4\n\nğŸ“œ CODEX LEDGER\nâ€¢ Daily Proclamations: 11\nâ€¢ Ledger Status: ACTIVE\nâ€¢ Last Update: 2025-11-08T04:17:43\n\nğŸ”¥ DIGITAL SOVEREIGNTY STATUS: ğŸ”´ CRITICAL\n\nâ•â•â•â•â•â•â•â•â•â•â•â•â•â•â•â•â•â•â•â•â•â•â•â•â•â•â•â•â•â•â•â•â•â•â•â•â•â•â•â•â•â•â•â•â•â•â•â•â•â•â•\nGenerated by Codex Dawn Dispatch System v2.0\nPowered by The Merritt Methodâ„¢",
    "metrics": {
      "store": {
        "revenue": "$0.00",
        "orders": 0,
        "status": "OFFLINE",
        "avg_order_value": "$0.00"
      },
      "social": {
        "twitter_posts": 0,
        "buffer_posts": 0,
        "total_interactions": 0,
        "platform_status": ["Twitter: OFFLINE", "Buffer: 0 platforms"],
        "connected_platforms": 0
      },
      "system": {
        "uptime": "Systems CRITICAL",
        "services": {
          "Dashboard": true,
          "WooCommerce": false,
          "Twitter": false,
          "Buffer": false
        },
        "health_score": 25.0
      },
      "ledger": {
        "proclamations": 11,
        "status": "ACTIVE",
        "last_update": "2025-11-08T04:17:43.458412"
      }
    }
  }
]
